README.md
setup.cfg
setup.py
CyclicGeneratedTMX.egg-info/PKG-INFO
CyclicGeneratedTMX.egg-info/SOURCES.txt
CyclicGeneratedTMX.egg-info/dependency_links.txt
CyclicGeneratedTMX.egg-info/requires.txt
CyclicGeneratedTMX.egg-info/top_level.txt
cyclicgentmx/__init__.py
cyclicgentmx/helpers.py
cyclicgentmx/map_base.py
cyclicgentmx/map_create.py
cyclicgentmx/map_image.py
cyclicgentmx/map_load.py
cyclicgentmx/map_save.py
cyclicgentmx/map_valid.py
cyclicgentmx/tmx_types.py