Metadata-Version: 1.2
Name: CyclicGeneratedTMX
Version: 0.1.3
Summary: Read, change, write, generate, create animated images TMX maps.
Home-page: https://github.com/yobagram/cyclic-gen-tmx
Author: yobagram
License: MIT
Download-URL: https://github.com/yobagram/cyclic-gen-tmx/archive/v_013.tar.gz
Keywords: tmx,map,generation,save,image
Platform: UNKNOWN
Classifier: Development Status :: 3 - Alpha
Classifier: Intended Audience :: Developers
Classifier: Topic :: Software Development :: Build Tools
Classifier: License :: OSI Approved :: MIT License
Classifier: Programming Language :: Python :: 3
Requires-Python: >=3.7
